django_otel/__init__.py
django_otel/apps.py
django_otel/config.py
django_otel/logger.py
django_otel/otel.py
django_otel-0.1.0.dist-info/METADATA
django_otel-0.1.0.dist-info/WHEEL
django_otel-0.1.0.dist-info/top_level.txt
django_otel-0.1.0.dist-info/RECORD
